db_build/__init__.py
db_build/cli.py
db_build/sqlite_utils_plugin.py
db_build-0.1.dist-info/METADATA
db_build-0.1.dist-info/WHEEL
db_build-0.1.dist-info/entry_points.txt
db_build-0.1.dist-info/top_level.txt
db_build-0.1.dist-info/RECORD
