Metadata-Version: 2.1
Name: db-build
Version: 0.1
Summary: Tools for building SQLite databases from files and directories
Author: Simon Willison
License: Apache-2.0
Project-URL: Homepage, https://github.com/simonw/db-buld
Project-URL: Changelog, https://github.com/simonw/db-buld/releases
Project-URL: Issues, https://github.com/simonw/db-buld/issues
Project-URL: CI, https://github.com/simonw/db-buld/actions
Classifier: License :: OSI Approved :: Apache Software License
Requires-Dist: click
Requires-Dist: sqlite-utils
Provides-Extra: test
Requires-Dist: pytest ; extra == 'test'
